MANIFEST.in
README.rst
setup.py
Products/__init__.py
Products.ATCustomizableView.egg-info/PKG-INFO
Products.ATCustomizableView.egg-info/SOURCES.txt
Products.ATCustomizableView.egg-info/dependency_links.txt
Products.ATCustomizableView.egg-info/entry_points.txt
Products.ATCustomizableView.egg-info/namespace_packages.txt
Products.ATCustomizableView.egg-info/not-zip-safe
Products.ATCustomizableView.egg-info/requires.txt
Products.ATCustomizableView.egg-info/top_level.txt
Products/ATCustomizableView/__init__.py
Products/ATCustomizableView/configure.zcml
Products/ATCustomizableView/interfaces.py
Products/ATCustomizableView/menu.py
Products/ATCustomizableView/overrides.zcml
Products/ATCustomizableView/patches.py
Products/ATCustomizableView/patches.zcml
Products/ATCustomizableView/tests.py
Products/ATCustomizableView/Extensions/install.py
Products/ATCustomizableView/browser/__init__.py
Products/ATCustomizableView/browser/configure.zcml
Products/ATCustomizableView/browser/customize-viewmenu.pt
Products/ATCustomizableView/browser/view.py
Products/ATCustomizableView/locales/Products.ATCustomizableView-manual.pot
Products/ATCustomizableView/locales/Products.ATCustomizableView.pot
Products/ATCustomizableView/locales/i18n.sh
Products/ATCustomizableView/locales/it/LC_MESSAGES/Products.ATCustomizableView.po
Products/ATCustomizableView/profiles/default/browserlayer.xml
Products/ATCustomizableView/profiles/default/metadata.xml
Products/ATCustomizableView/profiles/uninstall/browserlayer.xml
docs/HISTORY.txt
docs/INSTALL.txt
docs/LICENSE.GPL
docs/LICENSE.txt