Metadata-Version: 1.1
Name: Products.ATCustomizableView
Version: 0.5.0
Summary: A Plone product that change the standard Plone behaviour of the "Display" menu
Home-page: http://plone.org/products/atcustomizableview
Author: keul
Author-email: luca@keul.it
License: GPL
Keywords: plone atct default-view layout
Platform: UNKNOWN
Classifier: Framework :: Plone
Classifier: Framework :: Plone :: 3.3
Classifier: Framework :: Plone :: 4.0
Classifier: Framework :: Plone :: 4.1
Classifier: Framework :: Plone :: 4.2
Classifier: Framework :: Plone :: 4.3
Classifier: Programming Language :: Python
Classifier: Development Status :: 5 - Production/Stable
Classifier: Topic :: Software Development :: Libraries :: Python Modules
